LICENSE.md
README.md
setup.cfg
setup.py
src/mvem/__init__.py
src/mvem.egg-info/PKG-INFO
src/mvem.egg-info/SOURCES.txt
src/mvem.egg-info/dependency_links.txt
src/mvem.egg-info/requires.txt
src/mvem.egg-info/top_level.txt
src/mvem/mixture/__init__.py
src/mvem/mixture/skewnorm.py
src/mvem/stats/__init__.py
src/mvem/stats/gig.py
src/mvem/stats/multivariate_genhyperbolic.py
src/mvem/stats/multivariate_genskewt.py
src/mvem/stats/multivariate_hyperbolic.py
src/mvem/stats/multivariate_norm.py
src/mvem/stats/multivariate_norminvgauss.py
src/mvem/stats/multivariate_skewnorm.py
src/mvem/stats/multivariate_t.py
src/mvem/stats/multivariate_vargamma.py