Metadata-Version: 2.1
Name: mvem
Version: 0.1.4
Summary: Maximum likelihood estimation in multivariate probability distributions using EM algorithms
Home-page: https://github.com/krisskul/multivariate_em
Author: Kristoffer Skuland
Author-email: kristoffer.skuland@gmail.com
License: wtfpl
Keywords: maximum likelihood parameter estimation multivariate probability distribution EM algorithm
Platform: UNKNOWN
Requires-Python: >=3.6
License-File: LICENSE.md
